invoice_lint/__init__.py
invoice_lint/artifact_manager.py
invoice_lint/cli.py
invoice_lint/validator.py
python_invoice_lint-1.0.0.dist-info/METADATA
python_invoice_lint-1.0.0.dist-info/WHEEL
python_invoice_lint-1.0.0.dist-info/entry_points.txt
python_invoice_lint-1.0.0.dist-info/licenses/LICENSE
python_invoice_lint-1.0.0.dist-info/RECORD
