Metadata-Version: 2.4
Name: python-invoice-lint
Version: 1.0.0
Summary: EN16931 Invoice Validation Tool
Project-URL: Repository, https://github.com/your-org/invoice-lint
Project-URL: Bug Tracker, https://github.com/your-org/invoice-lint/issues
Author-email: Your Name <your.email@example.com>
License: Copyright (c) 2025 Your Organization
License-File: LICENSE
Classifier: Development Status :: 4 - Beta
Classifier: Intended Audience :: Developers
Classifier: License :: Other/Proprietary License
Classifier: Programming Language :: Python :: 3
Classifier: Programming Language :: Python :: 3.10
Classifier: Topic :: Office/Business :: Financial :: Accounting
Requires-Python: >=3.10
Requires-Dist: click>=8.1.7
Requires-Dist: lxml>=5.3.0
Requires-Dist: requests>=2.32.3
Requires-Dist: saxonche>=12.0.0
